oop_guessing_game
