Metadata-Version: 1.0
Name: oop-guessing-game
Version: 0.2
Summary: Simple modularized game between two players where one picks a number within a specific range and the other one guesses it
Home-page: UNKNOWN
Author: UNKNOWN
Author-email: UNKNOWN
License: UNKNOWN
Platform: UNKNOWN
